KwoksTool/__init__.py
KwoksTool/_version.py
KwoksTool/function.py
KwoksTool/info.py
KwoksTool/model.py
KwoksTool/spider.py
KwoksTool/Function/RecordScreen.py
KwoksTool/Show/function.py
KwoksTool/Spider/function.py
KwoksTool/Spider/stock.py
KwoksTool/source/IpPool.py
KwoksTool-23.9.16.1.dist-info/METADATA
KwoksTool-23.9.16.1.dist-info/WHEEL
KwoksTool-23.9.16.1.dist-info/top_level.txt
KwoksTool-23.9.16.1.dist-info/RECORD
