Metadata-Version: 2.1
Name: KwoksTool
Version: 23.9.16.1
Requires-Dist: altgraph ==0.17.3
Requires-Dist: attrs ==23.1.0
Requires-Dist: beautifulsoup4 ==4.12.2
Requires-Dist: bleach ==6.0.0
Requires-Dist: blinker ==1.6.2
Requires-Dist: bs4 ==0.0.1
Requires-Dist: build ==0.10.0
Requires-Dist: certifi ==2023.7.22
Requires-Dist: cffi ==1.15.1
Requires-Dist: charset-normalizer ==3.2.0
Requires-Dist: click ==8.1.6
Requires-Dist: colorama ==0.4.6
Requires-Dist: docutils ==0.20.1
Requires-Dist: et-xmlfile ==1.1.0
Requires-Dist: exceptiongroup ==1.1.2
Requires-Dist: Flask ==2.3.2
Requires-Dist: h11 ==0.14.0
Requires-Dist: idna ==3.4
Requires-Dist: importlib-metadata ==6.8.0
Requires-Dist: itsdangerous ==2.1.2
Requires-Dist: jaraco.classes ==3.3.0
Requires-Dist: Jinja2 ==3.1.2
Requires-Dist: keyring ==24.2.0
Requires-Dist: lxml ==4.9.3
Requires-Dist: markdown-it-py ==3.0.0
Requires-Dist: MarkupSafe ==2.1.3
Requires-Dist: mdurl ==0.1.2
Requires-Dist: more-itertools ==10.1.0
Requires-Dist: numpy ==1.25.2
Requires-Dist: openpyxl ==3.1.2
Requires-Dist: outcome ==1.2.0
Requires-Dist: packaging ==23.1
Requires-Dist: pandas ==2.0.3
Requires-Dist: pefile ==2023.2.7
Requires-Dist: pkginfo ==1.9.6
Requires-Dist: prettytable ==3.8.0
Requires-Dist: pycparser ==2.21
Requires-Dist: pyecharts ==2.0.3
Requires-Dist: PyExecJS ==1.5.1
Requires-Dist: Pygments ==2.16.1
Requires-Dist: pyinstaller ==5.13.0
Requires-Dist: pyinstaller-hooks-contrib ==2023.6
Requires-Dist: pyproject-hooks ==1.0.0
Requires-Dist: PySocks ==1.7.1
Requires-Dist: python-dateutil ==2.8.2
Requires-Dist: pytz ==2023.3
Requires-Dist: pywin32-ctypes ==0.2.2
Requires-Dist: readme-renderer ==40.0
Requires-Dist: requests ==2.31.0
Requires-Dist: requests-toolbelt ==1.0.0
Requires-Dist: rfc3986 ==2.0.0
Requires-Dist: rich ==13.5.2
Requires-Dist: selenium ==4.9.0
Requires-Dist: simplejson ==3.19.1
Requires-Dist: six ==1.16.0
Requires-Dist: sniffio ==1.3.0
Requires-Dist: sortedcontainers ==2.4.0
Requires-Dist: soupsieve ==2.4.1
Requires-Dist: tomli ==2.0.1
Requires-Dist: trio ==0.22.2
Requires-Dist: trio-websocket ==0.10.3
Requires-Dist: tushare ==1.2.89
Requires-Dist: twine ==4.0.2
Requires-Dist: tzdata ==2023.3
Requires-Dist: urllib3 ==1.26.16
Requires-Dist: wcwidth ==0.2.6
Requires-Dist: webencodings ==0.5.1
Requires-Dist: websocket-client ==0.57.0
Requires-Dist: Werkzeug ==2.3.6
Requires-Dist: wsproto ==1.2.0
Requires-Dist: zipp ==3.16.2
Requires-Dist: xlrd ==2.0.1
Requires-Dist: matplotlib ==3.7.2
Requires-Dist: pynput ==1.7.6
Requires-Dist: opencv-python ==4.8.0.76
